aiostipy/__init__.py
aiostipy/cli/__init__.py
aiostipy/cli/cli.py
aiostipy/cli/cli_handlers.py
aiostipy/common/__init__.py
aiostipy/common/decorators/__init__.py
aiostipy/common/decorators/controller.py
aiostipy/common/decorators/http/__init__.py
aiostipy/common/decorators/http/methods.py
aiostipy/common/decorators/module.py
aiostipy/common/decorators/service.py
aiostipy/core/__init__.py
aiostipy/core/applications.py
aiostipy/core/container.py
aiostipy/core/factory.py
aiostipy/responses.py
aiostipy/security.py
aiostipy-0.0.0.dist-info/LICENSE
aiostipy-0.0.0.dist-info/METADATA
aiostipy-0.0.0.dist-info/WHEEL
aiostipy-0.0.0.dist-info/RECORD
