Metadata-Version: 2.1
Name: aiostipy
Version: 0.0.0
Summary: A python framework build on top of aiohttp with a Nestjs like architecture
License: Apache 2.0
Author: Agustin Arce
Author-email: agustinarceprincich@gmail.com
Requires-Python: >=3.9,<4.0
Classifier: License :: Other/Proprietary License
Classifier: Programming Language :: Python :: 3
Classifier: Programming Language :: Python :: 3.9
Classifier: Programming Language :: Python :: 3.10
Classifier: Programming Language :: Python :: 3.11
Classifier: Programming Language :: Python :: 3.12
Requires-Dist: aiohttp (>=3.9.5,<4.0.0)
Requires-Dist: pytest-aiohttp (>=1.0.5,<2.0.0)
Requires-Dist: typing-extensions (>=4.12.2,<5.0.0)
